README.txt
setup.py
pessimum/__init__.py
pessimum/durations_report.py
pessimum/pessimum.py
pessimum/print_durations.py
pessimum.egg-info/PKG-INFO
pessimum.egg-info/SOURCES.txt
pessimum.egg-info/dependency_links.txt
pessimum.egg-info/entry_points.txt
pessimum.egg-info/requires.txt
pessimum.egg-info/top_level.txt
pessimum/utils/__init__.py
pessimum/utils/lazy.py
pessimum/utils/shims.py