Metadata-Version: 1.0
Name: pessimum
Version: 0.0.2
Summary: Tells you the top 10 longest running tests in your run
Home-page: https://github.com/hugobast/pessimum.git
Author: Hugo Bastien
Author-email: hugobast@gmail.com
License: MIT License
Platform: UNKNOWN
